frappy/RELEASE-VERSION
frappy/__init__.py
frappy/config.py
frappy/core.py
frappy/datatypes.py
frappy/dynamic.py
frappy/errors.py
frappy/extparams.py
frappy/features.py
frappy/io.py
frappy/logging.py
frappy/mixins.py
frappy/modulebase.py
frappy/modules.py
frappy/params.py
frappy/persistent.py
frappy/playground.py
frappy/properties.py
frappy/proxy.py
frappy/rwhandler.py
frappy/secnode.py
frappy/server.py
frappy/simulation.py
frappy/states.py
frappy/version.py
frappy/client/__init__.py
frappy/client/interactive.py
frappy/gui/__init__.py
frappy/gui/collapsible.py
frappy/gui/connection.py
frappy/gui/console.py
frappy/gui/inputwidgets.py
frappy/gui/logwindow.py
frappy/gui/mainwindow.py
frappy/gui/moduleoverview.py
frappy/gui/modulewidget.py
frappy/gui/nodewidget.py
frappy/gui/paramview.py
frappy/gui/plotting.py
frappy/gui/qt.py
frappy/gui/resources_qt5.py
frappy/gui/resources_qt6.py
frappy/gui/tabwidget.py
frappy/gui/util.py
frappy/gui/valuewidgets.py
frappy/gui/cfg_editor/__init__.py
frappy/gui/cfg_editor/config_file.py
frappy/gui/cfg_editor/mainwindow.py
frappy/gui/cfg_editor/node_display.py
frappy/gui/cfg_editor/tree_widget_item.py
frappy/gui/cfg_editor/utils.py
frappy/gui/cfg_editor/widgets.py
frappy/gui/params/__init__.py
frappy/gui/ui/cmdbuttons.ui
frappy/gui/ui/cmddialog.ui
frappy/gui/ui/console.ui
frappy/gui/ui/greeter.ui
frappy/gui/ui/logwindow.ui
frappy/gui/ui/mainwin.ui
frappy/gui/ui/modulewidget.ui
frappy/gui/ui/nodewidget.ui
frappy/gui/ui/parambuttons.ui
frappy/gui/ui/parambuttons_select.ui
frappy/gui/ui/paramview.ui
frappy/lib/__init__.py
frappy/lib/asynconn.py
frappy/lib/classdoc.py
frappy/lib/enum.py
frappy/lib/multievent.py
frappy/lib/pidfile.py
frappy/lib/sequence.py
frappy/lib/statemachine.py
frappy/protocol/__init__.py
frappy/protocol/discovery.py
frappy/protocol/dispatcher.py
frappy/protocol/messages.py
frappy/protocol/router.py
frappy/protocol/interface/__init__.py
frappy/protocol/interface/handler.py
frappy/protocol/interface/tcp.py
frappy_core-0.20.7.dist-info/METADATA
frappy_core-0.20.7.dist-info/WHEEL
frappy_core-0.20.7.dist-info/top_level.txt
frappy_core-0.20.7.dist-info/RECORD
