Metadata-Version: 2.1
Name: frappy-core
Version: 0.20.7
Summary: Implementation of SECoP server and client
Home-page: https://github.com/SampleEnvironment/frappy
Author: Enrico Faulhaber
Author-email: enrico.faulhaber@frm2.tum.de
License: GPL-2.0+
Classifier: Development Status :: 5 - Production/Stable
Classifier: Intended Audience :: Developers
Classifier: Intended Audience :: Science/Research
Classifier: Natural Language :: English
Classifier: License :: OSI Approved :: GNU General Public License v2 or later (GPLv2+)
Classifier: Operating System :: OS Independent
Classifier: Programming Language :: Python
Classifier: Programming Language :: Python :: 3
Classifier: Programming Language :: Python :: 3.9
Classifier: Topic :: Scientific/Engineering
Classifier: Topic :: Scientific/Engineering :: Human Machine Interfaces
Classifier: Topic :: Scientific/Engineering :: Physics
Requires-Dist: pyserial
Requires-Dist: mlzlog
Requires-Dist: psutil
Requires-Dist: python-daemon
